httpdecolib/__init__.py
httpdecolib/main.py
httpdecolib/request_interfaces/__init__.py
httpdecolib/request_interfaces/default_interface.py
httpdecolib/request_interfaces/get_interface.py
httpdecolib/request_interfaces/post_interface.py
httpdecolib-0.0.10.dist-info/LICENSE
httpdecolib-0.0.10.dist-info/METADATA
httpdecolib-0.0.10.dist-info/WHEEL
httpdecolib-0.0.10.dist-info/top_level.txt
httpdecolib-0.0.10.dist-info/RECORD
