Metadata-Version: 2.1
Name: httpdecolib
Version: 0.0.10
Summary: Easy http server using decorators
Home-page: https://github.com/FunDan3/httpdecolib/
Author: Fun_Dan3
Author-email: dfr34560@gmail.com
Project-URL: Bug Tracker, https://github.com/FunDan3/httpdecolib/issues
Classifier: Programming Language :: Python :: 3
Classifier: License :: OSI Approved :: GNU General Public License v3 (GPLv3)
Classifier: Operating System :: OS Independent
License-File: LICENSE
